djangautomate/__init__.py
djangautomate/core.py
djangautomate/generators.py
djangautomate/utils.py
djangautomate-0.1.0.dist-info/METADATA
djangautomate-0.1.0.dist-info/WHEEL
djangautomate-0.1.0.dist-info/RECORD
