Metadata-Version: 2.3
Name: djangautomate
Version: 0.1.0
Summary: Automates Django app, model, serializer, and view generation from SQLAlchemy tables
License: MIT
Author: William R. Astley
Author-email: william.astley@yourdomain.com
Requires-Python: >=3.12,<4.0
Classifier: License :: OSI Approved :: MIT License
Classifier: Programming Language :: Python :: 3
Classifier: Programming Language :: Python :: 3.12
Classifier: Programming Language :: Python :: 3.13
Requires-Dist: build (>=1.2.2.post1,<2.0.0)
Requires-Dist: django (>=4.2,<5.0)
Requires-Dist: numpy (>=1.26.0,<2.0.0)
Requires-Dist: pandas (>=2.2.0,<3.0.0)
Requires-Dist: sqlalchemy (>=2.0,<3.0)
Requires-Dist: twine (>=6.1.0,<7.0.0)
Project-URL: Homepage, https://djangautomate.readthedocs.io
Project-URL: Repository, https://github.com/pr1m8/djangautomate
